BMDanalyse/BMDanalyse.py
BMDanalyse/MainWindow.py
BMDanalyse/MatplotlibWidget.py
BMDanalyse/ROI.py
BMDanalyse/SidePanel.py
BMDanalyse/TableWidget.py
BMDanalyse/ViewBoxCustom.py
BMDanalyse/__init__.py
BMDanalyse/changeLog.txt
BMDanalyse/customItems.py
BMDanalyse/version.py
BMDanalyse/icons/README.txt
BMDanalyse/icons/arrow-down-2.png
BMDanalyse/icons/arrow-left.png
BMDanalyse/icons/arrow-right.png
BMDanalyse/icons/arrow-up-2.png
BMDanalyse/icons/bmdAnalyseLogo.svg
BMDanalyse/icons/file_add.png
BMDanalyse/icons/file_copy.png
BMDanalyse/icons/file_delete2.png
BMDanalyse/icons/filesave.png
BMDanalyse/icons/green-add3.png
BMDanalyse/icons/logo.png
BMDanalyse/icons/opened-folder.png
BMDanalyse/icons/polygonIcon.png
BMDanalyse/icons/rectangularIcon.png
BMDanalyse/icons/red_delete.png
BMDanalyse/sampleMedicalImages/Implant/XYplane/vxray_XY_1.png
BMDanalyse/sampleMedicalImages/Implant/XYplane/vxray_XY_11.png
BMDanalyse/sampleMedicalImages/Implant/XYplane/vxray_XY_21.png
BMDanalyse/sampleMedicalImages/Implant/XYplane/vxray_XY_31.png
BMDanalyse/sampleMedicalImages/Implant/XYplane/vxray_XY_6.png
BMDanalyse/sampleMedicalImages/Implant/YZplane/vxray_YZ_1.png
BMDanalyse/sampleMedicalImages/Implant/YZplane/vxray_YZ_11.png
BMDanalyse/sampleMedicalImages/Implant/YZplane/vxray_YZ_21.png
BMDanalyse/sampleMedicalImages/Implant/YZplane/vxray_YZ_31.png
BMDanalyse/sampleMedicalImages/Implant/YZplane/vxray_YZ_6.png
BMDanalyse/sampleMedicalImages/No implant/XYplane/noimplant_XY_1.png
BMDanalyse/sampleMedicalImages/No implant/XYplane/noimplant_XY_11.png
BMDanalyse/sampleMedicalImages/No implant/XYplane/noimplant_XY_21.png
BMDanalyse/sampleMedicalImages/No implant/XYplane/noimplant_XY_31.png
BMDanalyse/sampleMedicalImages/No implant/XYplane/noimplant_XY_6.png
BMDanalyse/sampleMedicalImages/No implant/YZplane/noimplant_YZ_1.png
BMDanalyse/sampleMedicalImages/No implant/YZplane/noimplant_YZ_11.png
BMDanalyse-0.2.0.dist-info/DESCRIPTION.rst
BMDanalyse-0.2.0.dist-info/METADATA
BMDanalyse-0.2.0.dist-info/RECORD
BMDanalyse-0.2.0.dist-info/WHEEL
BMDanalyse-0.2.0.dist-info/entry_points.txt
BMDanalyse-0.2.0.dist-info/metadata.json
BMDanalyse-0.2.0.dist-info/top_level.txt
