Metadata-Version: 2.0
Name: BMDanalyse
Version: 0.2.0
Summary: Tool to analyse regional changes in a time series of 2D medical images.
Home-page: http://pypi.python.org/pypi/BMDanalyse/
Author: Michael Hogg
Author-email: michael.christopher.hogg@gmail.com
License: MIT license
Download-URL: https://pypi.python.org/packages/source/B/BMDanalyse/BMDanalyse-0.2.0.zip
Keywords: python,medical,image,analysis,ROIs,xray
Platform: UNKNOWN
Classifier: Programming Language :: Python
Classifier: Programming Language :: Python :: 2
Classifier: Programming Language :: Python :: 2.7
Classifier: Development Status :: 4 - Beta
Classifier: Environment :: Other Environment
Classifier: Intended Audience :: Healthcare Industry
Classifier: Intended Audience :: Science/Research
Classifier: License :: OSI Approved :: MIT License
Classifier: Operating System :: OS Independent
Classifier: Topic :: Scientific/Engineering :: Medical Science Apps.
Classifier: Topic :: Scientific/Engineering :: Visualization
Requires-Dist: matplotlib
Requires-Dist: numpy
Requires-Dist: pillow
Requires-Dist: pyqtgraph
